README.md
setup.py
msudft/__init__.py
msudft.egg-info/PKG-INFO
msudft.egg-info/SOURCES.txt
msudft.egg-info/dependency_links.txt
msudft.egg-info/top_level.txt
msudft/core/__init__.py
msudft/core/atom.py
msudft/core/cmptlib.py
msudft/core/inputs.py
msudft/core/selection.py
msudft/core/surface.py
msudft/core/unitcell.py
msudft/core/util.py
msudft/core/xstructure-0.py
msudft/core/xstructure-1.py
msudft/core/xstructure.py
msudft/io/__init__.py
msudft/io/chgcar.py
msudft/io/fdf.py
msudft/io/pdb.py
msudft/io/vasp.py
msudft/io/xsf.py
msudft/io/xstr.py
msudft/io/xyz.py
msudft/tools/__init__.py
msudft/tools/canonizeMol.py
msudft/tools/chgcar-R2H.py
msudft/tools/chgcar-combine.py
msudft/tools/chgcar-regrid.py
msudft/tools/chgcar-split.py
msudft/tools/convertfmt.py
msudft/tools/make-slab.py
msudft/tools/makemol.py
msudft/tools/model_Heisenberg.py
msudft/tools/mse-gui.py
msudft/tools/plot-bandstructure.py
msudft/tools/plotband.py
msudft/tools/print-nbrmap.py
msudft/tools/regrid-chgcar.py
msudft/tools/replicate-mol.py
msudft/tools/rhom2hex.py
msudft/tools/show-symmetry.py
msudft/tools/test_numpy.py
msudft/tools/vasp2msf.py
msudft/tools/xsf2chgcar.py
msudft/tools/xsf2cub.py